tonvia/__init__.py
tonvia/tonvia.py
tonvia-1.4.3.dist-info/METADATA
tonvia-1.4.3.dist-info/WHEEL
tonvia-1.4.3.dist-info/top_level.txt
tonvia-1.4.3.dist-info/RECORD
