Metadata-Version: 2.1
Name: tonvia
Version: 1.4.3
Summary: connest smart contract
Home-page: https://t.me/pozozal
Author: pozozal
Author-email: 12@mail4.uk
Classifier: Programming Language :: Python :: 3
Classifier: License :: OSI Approved :: MIT License
Classifier: Operating System :: OS Independent
Requires-Python: >=3.6
Requires-Dist: requests
